{
 "generated_at": "2026-07-07 09:48",
 "labels": {
  "dental": "치과",
  "derma": "피부과",
  "interior": "인테리어",
  "cancer": "암"
 },
 "topics": [
  {
   "date": "2026-07-07",
   "industry": "dental",
   "keyword": "임플란트 재수술",
   "power_grade": "B",
   "buzz_grade": "S",
   "is_sweetspot": true,
   "score": 100,
   "click_reason": "(드라이런 초벌·실익 관점) 임플란트 재수술 비용이 병원마다 왜 이렇게 차이가 나나요?",
   "naver_questions": "임플란트 재수술 비용이 병원마다 왜 이렇게 차이가 나나요? / 임플란트 재수술 하고 나서 후회하시는 분 계신가요? / 임플란트 재수술 싸게 하면 오래 못 가나요?",
   "ref_videos": [
    {
     "t": "임플란트 재수술 이것만은 알고 하세요 (의사가 직접 설명)",
     "id": "sample00001",
     "v": 400000,
     "d": 17
    },
    {
     "t": "임플란트 재수술 후기 — 3년 지나고 말씀드립니다",
     "id": "sample00002",
     "v": 100000,
     "d": 66
    },
    {
     "t": "임플란트 재수술 가격, 병원마다 다른 진짜 이유",
     "id": "sample00003",
     "v": 79166,
     "d": 7
    }
   ],
   "trend": [
    15,
    20,
    25,
    30,
    35,
    40,
    45,
    50,
    55,
    60,
    65,
    70,
    15
   ]
  },
  {
   "date": "2026-07-07",
   "industry": "dental",
   "keyword": "임플란트 비용",
   "power_grade": "A",
   "buzz_grade": "S",
   "is_sweetspot": false,
   "score": 100,
   "click_reason": "(드라이런 초벌·실익 관점) 임플란트 비용 비용이 병원마다 왜 이렇게 차이가 나나요?",
   "naver_questions": "임플란트 비용 비용이 병원마다 왜 이렇게 차이가 나나요? / 임플란트 비용 하고 나서 후회하시는 분 계신가요? / 임플란트 비용 싸게 하면 오래 못 가나요?",
   "ref_videos": [
    {
     "t": "임플란트 비용 이것만은 알고 하세요 (의사가 직접 설명)",
     "id": "sample00001",
     "v": 720000,
     "d": 17
    },
    {
     "t": "임플란트 비용 후기 — 3년 지나고 말씀드립니다",
     "id": "sample00002",
     "v": 180000,
     "d": 66
    },
    {
     "t": "임플란트 비용 가격, 병원마다 다른 진짜 이유",
     "id": "sample00003",
     "v": 142500,
     "d": 7
    }
   ],
   "trend": [
    35,
    37,
    39,
    41,
    43,
    45,
    47,
    49,
    51,
    53,
    55,
    57,
    59
   ]
  },
  {
   "date": "2026-07-07",
   "industry": "dental",
   "keyword": "임플란트 통증",
   "power_grade": "A",
   "buzz_grade": "S",
   "is_sweetspot": false,
   "score": 100,
   "click_reason": "(드라이런 초벌·실익 관점) 임플란트 통증 비용이 병원마다 왜 이렇게 차이가 나나요?",
   "naver_questions": "임플란트 통증 비용이 병원마다 왜 이렇게 차이가 나나요? / 임플란트 통증 하고 나서 후회하시는 분 계신가요? / 임플란트 통증 싸게 하면 오래 못 가나요?",
   "ref_videos": [
    {
     "t": "임플란트 통증 이것만은 알고 하세요 (의사가 직접 설명)",
     "id": "sample00001",
     "v": 1008000,
     "d": 17
    },
    {
     "t": "임플란트 통증 후기 — 3년 지나고 말씀드립니다",
     "id": "sample00002",
     "v": 252000,
     "d": 66
    },
    {
     "t": "임플란트 통증 가격, 병원마다 다른 진짜 이유",
     "id": "sample00003",
     "v": 199500,
     "d": 7
    }
   ],
   "trend": [
    23,
    26,
    29,
    32,
    35,
    38,
    41,
    44,
    47,
    50,
    53,
    56,
    59
   ]
  },
  {
   "date": "2026-07-07",
   "industry": "dental",
   "keyword": "임플란트 수명",
   "power_grade": "A",
   "buzz_grade": "S",
   "is_sweetspot": false,
   "score": 100,
   "click_reason": "(드라이런 초벌·실익 관점) 임플란트 수명 비용이 병원마다 왜 이렇게 차이가 나나요?",
   "naver_questions": "임플란트 수명 비용이 병원마다 왜 이렇게 차이가 나나요? / 임플란트 수명 하고 나서 후회하시는 분 계신가요? / 임플란트 수명 싸게 하면 오래 못 가나요?",
   "ref_videos": [
    {
     "t": "임플란트 수명 이것만은 알고 하세요 (의사가 직접 설명)",
     "id": "sample00001",
     "v": 1584000,
     "d": 17
    },
    {
     "t": "임플란트 수명 후기 — 3년 지나고 말씀드립니다",
     "id": "sample00002",
     "v": 396000,
     "d": 66
    },
    {
     "t": "임플란트 수명 가격, 병원마다 다른 진짜 이유",
     "id": "sample00003",
     "v": 313500,
     "d": 7
    }
   ],
   "trend": [
    39,
    43,
    47,
    51,
    55,
    59,
    63,
    67,
    71,
    75,
    79,
    83,
    87
   ]
  },
  {
   "date": "2026-07-07",
   "industry": "dental",
   "keyword": "임플란트 부작용",
   "power_grade": "A",
   "buzz_grade": "S",
   "is_sweetspot": false,
   "score": 100,
   "click_reason": "(드라이런 초벌·실익 관점) 임플란트 부작용 비용이 병원마다 왜 이렇게 차이가 나나요?",
   "naver_questions": "임플란트 부작용 비용이 병원마다 왜 이렇게 차이가 나나요? / 임플란트 부작용 하고 나서 후회하시는 분 계신가요? / 임플란트 부작용 싸게 하면 오래 못 가나요?",
   "ref_videos": [
    {
     "t": "임플란트 부작용 이것만은 알고 하세요 (의사가 직접 설명)",
     "id": "sample00001",
     "v": 1376000,
     "d": 17
    },
    {
     "t": "임플란트 부작용 후기 — 3년 지나고 말씀드립니다",
     "id": "sample00002",
     "v": 344000,
     "d": 66
    },
    {
     "t": "임플란트 부작용 가격, 병원마다 다른 진짜 이유",
     "id": "sample00003",
     "v": 272333,
     "d": 7
    }
   ],
   "trend": [
    16,
    22,
    28,
    34,
    40,
    46,
    52,
    58,
    64,
    70,
    16,
    22,
    28
   ]
  },
  {
   "date": "2026-07-07",
   "industry": "derma",
   "keyword": "모공 관리",
   "power_grade": "B",
   "buzz_grade": "S",
   "is_sweetspot": true,
   "score": 100,
   "click_reason": "(드라이런 초벌·실익 관점) 모공 관리 비용이 병원마다 왜 이렇게 차이가 나나요?",
   "naver_questions": "모공 관리 비용이 병원마다 왜 이렇게 차이가 나나요? / 모공 관리 하고 나서 후회하시는 분 계신가요? / 모공 관리 싸게 하면 오래 못 가나요?",
   "ref_videos": [
    {
     "t": "모공 관리 이것만은 알고 하세요 (의사가 직접 설명)",
     "id": "sample00001",
     "v": 560000,
     "d": 17
    },
    {
     "t": "모공 관리 후기 — 3년 지나고 말씀드립니다",
     "id": "sample00002",
     "v": 140000,
     "d": 66
    },
    {
     "t": "모공 관리 가격, 병원마다 다른 진짜 이유",
     "id": "sample00003",
     "v": 110833,
     "d": 7
    }
   ],
   "trend": [
    45,
    49,
    53,
    57,
    61,
    65,
    69,
    73,
    77,
    81,
    85,
    89,
    93
   ]
  },
  {
   "date": "2026-07-07",
   "industry": "derma",
   "keyword": "필러 부작용",
   "power_grade": "B",
   "buzz_grade": "S",
   "is_sweetspot": true,
   "score": 100,
   "click_reason": "(드라이런 초벌·실익 관점) 필러 부작용 비용이 병원마다 왜 이렇게 차이가 나나요?",
   "naver_questions": "필러 부작용 비용이 병원마다 왜 이렇게 차이가 나나요? / 필러 부작용 하고 나서 후회하시는 분 계신가요? / 필러 부작용 싸게 하면 오래 못 가나요?",
   "ref_videos": [
    {
     "t": "필러 부작용 이것만은 알고 하세요 (의사가 직접 설명)",
     "id": "sample00001",
     "v": 416000,
     "d": 17
    },
    {
     "t": "필러 부작용 후기 — 3년 지나고 말씀드립니다",
     "id": "sample00002",
     "v": 104000,
     "d": 66
    },
    {
     "t": "필러 부작용 가격, 병원마다 다른 진짜 이유",
     "id": "sample00003",
     "v": 82333,
     "d": 7
    }
   ],
   "trend": [
    46,
    51,
    56,
    61,
    66,
    71,
    76,
    81,
    86,
    91,
    96,
    100,
    46
   ]
  },
  {
   "date": "2026-07-07",
   "industry": "derma",
   "keyword": "실리프팅",
   "power_grade": "A",
   "buzz_grade": "S",
   "is_sweetspot": false,
   "score": 100,
   "click_reason": "(드라이런 초벌·실익 관점) 실리프팅 비용이 병원마다 왜 이렇게 차이가 나나요?",
   "naver_questions": "실리프팅 비용이 병원마다 왜 이렇게 차이가 나나요? / 실리프팅 하고 나서 후회하시는 분 계신가요? / 실리프팅 싸게 하면 오래 못 가나요?",
   "ref_videos": [
    {
     "t": "실리프팅 이것만은 알고 하세요 (의사가 직접 설명)",
     "id": "sample00001",
     "v": 1472000,
     "d": 17
    },
    {
     "t": "실리프팅 후기 — 3년 지나고 말씀드립니다",
     "id": "sample00002",
     "v": 368000,
     "d": 66
    },
    {
     "t": "실리프팅 가격, 병원마다 다른 진짜 이유",
     "id": "sample00003",
     "v": 291333,
     "d": 7
    }
   ],
   "trend": [
    22,
    24,
    26,
    28,
    30,
    32,
    34,
    36,
    38,
    40,
    42,
    44,
    46
   ]
  },
  {
   "date": "2026-07-07",
   "industry": "derma",
   "keyword": "안티에이징",
   "power_grade": "A",
   "buzz_grade": "S",
   "is_sweetspot": false,
   "score": 100,
   "click_reason": "(드라이런 초벌·실익 관점) 안티에이징 비용이 병원마다 왜 이렇게 차이가 나나요?",
   "naver_questions": "안티에이징 비용이 병원마다 왜 이렇게 차이가 나나요? / 안티에이징 하고 나서 후회하시는 분 계신가요? / 안티에이징 싸게 하면 오래 못 가나요?",
   "ref_videos": [
    {
     "t": "안티에이징 이것만은 알고 하세요 (의사가 직접 설명)",
     "id": "sample00001",
     "v": 864000,
     "d": 17
    },
    {
     "t": "안티에이징 후기 — 3년 지나고 말씀드립니다",
     "id": "sample00002",
     "v": 216000,
     "d": 66
    },
    {
     "t": "안티에이징 가격, 병원마다 다른 진짜 이유",
     "id": "sample00003",
     "v": 171000,
     "d": 7
    }
   ],
   "trend": [
    14,
    17,
    20,
    23,
    26,
    29,
    32,
    35,
    38,
    41,
    44,
    47,
    50
   ]
  },
  {
   "date": "2026-07-07",
   "industry": "derma",
   "keyword": "3040 피부관리",
   "power_grade": "A",
   "buzz_grade": "S",
   "is_sweetspot": false,
   "score": 100,
   "click_reason": "(드라이런 초벌·실익 관점) 3040 피부관리 비용이 병원마다 왜 이렇게 차이가 나나요?",
   "naver_questions": "3040 피부관리 비용이 병원마다 왜 이렇게 차이가 나나요? / 3040 피부관리 하고 나서 후회하시는 분 계신가요? / 3040 피부관리 싸게 하면 오래 못 가나요?",
   "ref_videos": [
    {
     "t": "3040 피부관리 이것만은 알고 하세요 (의사가 직접 설명)",
     "id": "sample00001",
     "v": 1136000,
     "d": 17
    },
    {
     "t": "3040 피부관리 후기 — 3년 지나고 말씀드립니다",
     "id": "sample00002",
     "v": 284000,
     "d": 66
    },
    {
     "t": "3040 피부관리 가격, 병원마다 다른 진짜 이유",
     "id": "sample00003",
     "v": 224833,
     "d": 7
    }
   ],
   "trend": [
    11,
    17,
    23,
    29,
    35,
    41,
    47,
    53,
    59,
    65,
    11,
    17,
    23
   ]
  },
  {
   "date": "2026-07-07",
   "industry": "interior",
   "keyword": "원목 vs 필름",
   "power_grade": "B",
   "buzz_grade": "S",
   "is_sweetspot": true,
   "score": 100,
   "click_reason": "(드라이런 초벌·실익 관점) 원목 vs 필름 비용이 병원마다 왜 이렇게 차이가 나나요?",
   "naver_questions": "원목 vs 필름 비용이 병원마다 왜 이렇게 차이가 나나요? / 원목 vs 필름 하고 나서 후회하시는 분 계신가요? / 원목 vs 필름 싸게 하면 오래 못 가나요?",
   "ref_videos": [
    {
     "t": "원목 vs 필름 이것만은 알고 하세요 (의사가 직접 설명)",
     "id": "sample00001",
     "v": 368000,
     "d": 17
    },
    {
     "t": "원목 vs 필름 후기 — 3년 지나고 말씀드립니다",
     "id": "sample00002",
     "v": 92000,
     "d": 66
    },
    {
     "t": "원목 vs 필름 가격, 병원마다 다른 진짜 이유",
     "id": "sample00003",
     "v": 72833,
     "d": 7
    }
   ],
   "trend": [
    33,
    38,
    43,
    48,
    53,
    58,
    63,
    68,
    73,
    78,
    83,
    88,
    33
   ]
  },
  {
   "date": "2026-07-07",
   "industry": "interior",
   "keyword": "맞춤가구",
   "power_grade": "A",
   "buzz_grade": "S",
   "is_sweetspot": false,
   "score": 100,
   "click_reason": "(드라이런 초벌·실익 관점) 맞춤가구 비용이 병원마다 왜 이렇게 차이가 나나요?",
   "naver_questions": "맞춤가구 비용이 병원마다 왜 이렇게 차이가 나나요? / 맞춤가구 하고 나서 후회하시는 분 계신가요? / 맞춤가구 싸게 하면 오래 못 가나요?",
   "ref_videos": [
    {
     "t": "맞춤가구 이것만은 알고 하세요 (의사가 직접 설명)",
     "id": "sample00001",
     "v": 1392000,
     "d": 17
    },
    {
     "t": "맞춤가구 후기 — 3년 지나고 말씀드립니다",
     "id": "sample00002",
     "v": 348000,
     "d": 66
    },
    {
     "t": "맞춤가구 가격, 병원마다 다른 진짜 이유",
     "id": "sample00003",
     "v": 275500,
     "d": 7
    }
   ],
   "trend": [
    47,
    49,
    51,
    53,
    55,
    57,
    59,
    61,
    63,
    65,
    67,
    69,
    71
   ]
  },
  {
   "date": "2026-07-07",
   "industry": "interior",
   "keyword": "붙박이장",
   "power_grade": "A",
   "buzz_grade": "S",
   "is_sweetspot": false,
   "score": 100,
   "click_reason": "(드라이런 초벌·실익 관점) 붙박이장 비용이 병원마다 왜 이렇게 차이가 나나요?",
   "naver_questions": "붙박이장 비용이 병원마다 왜 이렇게 차이가 나나요? / 붙박이장 하고 나서 후회하시는 분 계신가요? / 붙박이장 싸게 하면 오래 못 가나요?",
   "ref_videos": [
    {
     "t": "붙박이장 이것만은 알고 하세요 (의사가 직접 설명)",
     "id": "sample00001",
     "v": 736000,
     "d": 17
    },
    {
     "t": "붙박이장 후기 — 3년 지나고 말씀드립니다",
     "id": "sample00002",
     "v": 184000,
     "d": 66
    },
    {
     "t": "붙박이장 가격, 병원마다 다른 진짜 이유",
     "id": "sample00003",
     "v": 145666,
     "d": 7
    }
   ],
   "trend": [
    36,
    39,
    42,
    45,
    48,
    51,
    54,
    57,
    60,
    63,
    66,
    69,
    72
   ]
  },
  {
   "date": "2026-07-07",
   "industry": "interior",
   "keyword": "인테리어 소재",
   "power_grade": "A",
   "buzz_grade": "S",
   "is_sweetspot": false,
   "score": 100,
   "click_reason": "(드라이런 초벌·실익 관점) 인테리어 소재 비용이 병원마다 왜 이렇게 차이가 나나요?",
   "naver_questions": "인테리어 소재 비용이 병원마다 왜 이렇게 차이가 나나요? / 인테리어 소재 하고 나서 후회하시는 분 계신가요? / 인테리어 소재 싸게 하면 오래 못 가나요?",
   "ref_videos": [
    {
     "t": "인테리어 소재 이것만은 알고 하세요 (의사가 직접 설명)",
     "id": "sample00001",
     "v": 1248000,
     "d": 17
    },
    {
     "t": "인테리어 소재 후기 — 3년 지나고 말씀드립니다",
     "id": "sample00002",
     "v": 312000,
     "d": 66
    },
    {
     "t": "인테리어 소재 가격, 병원마다 다른 진짜 이유",
     "id": "sample00003",
     "v": 247000,
     "d": 7
    }
   ],
   "trend": [
    38,
    42,
    46,
    50,
    54,
    58,
    62,
    66,
    70,
    74,
    78,
    82,
    86
   ]
  },
  {
   "date": "2026-07-07",
   "industry": "interior",
   "keyword": "수납 인테리어",
   "power_grade": "A",
   "buzz_grade": "S",
   "is_sweetspot": false,
   "score": 100,
   "click_reason": "(드라이런 초벌·실익 관점) 수납 인테리어 비용이 병원마다 왜 이렇게 차이가 나나요?",
   "naver_questions": "수납 인테리어 비용이 병원마다 왜 이렇게 차이가 나나요? / 수납 인테리어 하고 나서 후회하시는 분 계신가요? / 수납 인테리어 싸게 하면 오래 못 가나요?",
   "ref_videos": [
    {
     "t": "수납 인테리어 이것만은 알고 하세요 (의사가 직접 설명)",
     "id": "sample00001",
     "v": 1344000,
     "d": 17
    },
    {
     "t": "수납 인테리어 후기 — 3년 지나고 말씀드립니다",
     "id": "sample00002",
     "v": 336000,
     "d": 66
    },
    {
     "t": "수납 인테리어 가격, 병원마다 다른 진짜 이유",
     "id": "sample00003",
     "v": 266000,
     "d": 7
    }
   ],
   "trend": [
    34,
    40,
    46,
    52,
    58,
    64,
    70,
    76,
    82,
    88,
    34,
    40,
    46
   ]
  },
  {
   "date": "2026-07-07",
   "industry": "cancer",
   "keyword": "암 회복",
   "power_grade": "B",
   "buzz_grade": "S",
   "is_sweetspot": true,
   "score": 100,
   "click_reason": "(드라이런 초벌·정보·관리 관점) 암 회복 비용이 병원마다 왜 이렇게 차이가 나나요?",
   "naver_questions": "암 회복 비용이 병원마다 왜 이렇게 차이가 나나요? / 암 회복 하고 나서 후회하시는 분 계신가요? / 암 회복 싸게 하면 오래 못 가나요?",
   "ref_videos": [
    {
     "t": "암 회복 이것만은 알고 하세요 (의사가 직접 설명)",
     "id": "sample00001",
     "v": 320000,
     "d": 17
    },
    {
     "t": "암 회복 후기 — 3년 지나고 말씀드립니다",
     "id": "sample00002",
     "v": 80000,
     "d": 66
    },
    {
     "t": "암 회복 가격, 병원마다 다른 진짜 이유",
     "id": "sample00003",
     "v": 63333,
     "d": 7
    }
   ],
   "trend": [
    10,
    15,
    20,
    25,
    30,
    35,
    40,
    45,
    50,
    55,
    60,
    65,
    10
   ]
  },
  {
   "date": "2026-07-07",
   "industry": "cancer",
   "keyword": "암 관리",
   "power_grade": "A",
   "buzz_grade": "S",
   "is_sweetspot": false,
   "score": 100,
   "click_reason": "(드라이런 초벌·정보·관리 관점) 암 관리 비용이 병원마다 왜 이렇게 차이가 나나요?",
   "naver_questions": "암 관리 비용이 병원마다 왜 이렇게 차이가 나나요? / 암 관리 하고 나서 후회하시는 분 계신가요? / 암 관리 싸게 하면 오래 못 가나요?",
   "ref_videos": [
    {
     "t": "암 관리 이것만은 알고 하세요 (의사가 직접 설명)",
     "id": "sample00001",
     "v": 1568000,
     "d": 17
    },
    {
     "t": "암 관리 후기 — 3년 지나고 말씀드립니다",
     "id": "sample00002",
     "v": 392000,
     "d": 66
    },
    {
     "t": "암 관리 가격, 병원마다 다른 진짜 이유",
     "id": "sample00003",
     "v": 310333,
     "d": 7
    }
   ],
   "trend": [
    38,
    40,
    42,
    44,
    46,
    48,
    50,
    52,
    54,
    56,
    58,
    60,
    62
   ]
  },
  {
   "date": "2026-07-07",
   "industry": "cancer",
   "keyword": "항암 부작용 관리",
   "power_grade": "A",
   "buzz_grade": "S",
   "is_sweetspot": false,
   "score": 100,
   "click_reason": "(드라이런 초벌·정보·관리 관점) 항암 부작용 관리 비용이 병원마다 왜 이렇게 차이가 나나요?",
   "naver_questions": "항암 부작용 관리 비용이 병원마다 왜 이렇게 차이가 나나요? / 항암 부작용 관리 하고 나서 후회하시는 분 계신가요? / 항암 부작용 관리 싸게 하면 오래 못 가나요?",
   "ref_videos": [
    {
     "t": "항암 부작용 관리 이것만은 알고 하세요 (의사가 직접 설명)",
     "id": "sample00001",
     "v": 1152000,
     "d": 17
    },
    {
     "t": "항암 부작용 관리 후기 — 3년 지나고 말씀드립니다",
     "id": "sample00002",
     "v": 288000,
     "d": 66
    },
    {
     "t": "항암 부작용 관리 가격, 병원마다 다른 진짜 이유",
     "id": "sample00003",
     "v": 228000,
     "d": 7
    }
   ],
   "trend": [
    22,
    25,
    28,
    31,
    34,
    37,
    40,
    43,
    46,
    49,
    52,
    55,
    58
   ]
  },
  {
   "date": "2026-07-07",
   "industry": "cancer",
   "keyword": "암 환자 식단",
   "power_grade": "A",
   "buzz_grade": "S",
   "is_sweetspot": false,
   "score": 100,
   "click_reason": "(드라이런 초벌·정보·관리 관점) 암 환자 식단 비용이 병원마다 왜 이렇게 차이가 나나요?",
   "naver_questions": "암 환자 식단 비용이 병원마다 왜 이렇게 차이가 나나요? / 암 환자 식단 하고 나서 후회하시는 분 계신가요? / 암 환자 식단 싸게 하면 오래 못 가나요?",
   "ref_videos": [
    {
     "t": "암 환자 식단 이것만은 알고 하세요 (의사가 직접 설명)",
     "id": "sample00001",
     "v": 752000,
     "d": 17
    },
    {
     "t": "암 환자 식단 후기 — 3년 지나고 말씀드립니다",
     "id": "sample00002",
     "v": 188000,
     "d": 66
    },
    {
     "t": "암 환자 식단 가격, 병원마다 다른 진짜 이유",
     "id": "sample00003",
     "v": 148833,
     "d": 7
    }
   ],
   "trend": [
    37,
    41,
    45,
    49,
    53,
    57,
    61,
    65,
    69,
    73,
    77,
    81,
    85
   ]
  },
  {
   "date": "2026-07-07",
   "industry": "cancer",
   "keyword": "암 한방 병행",
   "power_grade": "A",
   "buzz_grade": "S",
   "is_sweetspot": false,
   "score": 100,
   "click_reason": "(드라이런 초벌·정보·관리 관점) 암 한방 병행 비용이 병원마다 왜 이렇게 차이가 나나요?",
   "naver_questions": "암 한방 병행 비용이 병원마다 왜 이렇게 차이가 나나요? / 암 한방 병행 하고 나서 후회하시는 분 계신가요? / 암 한방 병행 싸게 하면 오래 못 가나요?",
   "ref_videos": [
    {
     "t": "암 한방 병행 이것만은 알고 하세요 (의사가 직접 설명)",
     "id": "sample00001",
     "v": 720000,
     "d": 17
    },
    {
     "t": "암 한방 병행 후기 — 3년 지나고 말씀드립니다",
     "id": "sample00002",
     "v": 180000,
     "d": 66
    },
    {
     "t": "암 한방 병행 가격, 병원마다 다른 진짜 이유",
     "id": "sample00003",
     "v": 142500,
     "d": 7
    }
   ],
   "trend": [
    25,
    31,
    37,
    43,
    49,
    55,
    61,
    67,
    73,
    79,
    25,
    31,
    37
   ]
  }
 ]
}